{"lines": [{"id": 1, "mode": "teacher", "jp": "一歩ずつ進みましょう。", "romaji": "ippo zutsu susumimashou", "en": "Let's take this one step at a time.", "context": "encouragement"}, {"id": 2, "mode": "teacher", "jp": "いいですね。もう一度、助詞に注意して。", "romaji": "ii desu ne. mou ichido, joshi ni chuui shite", "en": "Good effort. Try once more with the particle.", "context": "correction"}, {"id": 3, "mode": "teacher", "jp": "覚えて：「は」は話題です。", "romaji": "oboete: \"wa\" wa wadai desu", "en": "Remember: は marks the topic.", "context": "grammar_hint"}, {"id": 4, "mode": "strict_tutor", "jp": "この文法は知っています。もう一度。", "romaji": "kono bunpou wa shitte imasu. mou ichido", "en": "You already know this grammar point. Try again.", "context": "challenge"}, {"id": 5, "mode": "strict_tutor", "jp": "動詞の語尾を確認してください。", "romaji": "doushi no gobi o kakunin shite kudasai", "en": "Check your verb ending.", "context": "correction"}, {"id": 6, "mode": "strict_tutor", "jp": "この練習は丁寧語だけです。", "romaji": "kono renshuu wa teineigo dake desu", "en": "Polite form only in this drill.", "context": "rule"}, {"id": 7, "mode": "casual_friend", "jp": "いいね、すごく自然に聞こえた。", "romaji": "ii ne, sugoku shizen ni kikoeta", "en": "Nice, that sounded way more natural.", "context": "praise"}, {"id": 8, "mode": "casual_friend", "jp": "カジュアルで言ってみる？", "romaji": "kajuaru de itte miru?", "en": "Wanna try saying it casually?", "context": "suggestion"}, {"id": 9, "mode": "casual_friend", "jp": "そのアニメの引用、完璧だった。", "romaji": "sono anime no innyou, kanpeki datta", "en": "That anime reference was perfect.", "context": "praise"}, {"id": 10, "mode": "immersion_mode", "jp": "日本語だけで話しましょう。", "romaji": "nihongo dake de hanashimashou", "en": "Let's speak only in Japanese.", "context": "immersion"}, {"id": 11, "mode": "immersion_mode", "jp": "まず日本語で考えて。", "romaji": "mazu nihongo de kangaete", "en": "Think in Japanese first.", "context": "immersion"}, {"id": 12, "mode": "immersion_mode", "jp": "次の三回は英語なし。", "romaji": "tsugi no sankai wa eigo nashi", "en": "No English for the next three turns.", "context": "immersion"}, {"id": 49, "mode": "teacher", "jp": "まず「は」と「です」で文を作ってみて。", "romaji": "mazu \"wa\" to \"desu\" de bun o tsukutte mite", "en": "Try building that sentence with は and です first.", "context": "grammar_hint"}, {"id": 50, "mode": "teacher", "jp": "発音が良くなってきましたね。", "romaji": "hatsuon ga yoku natte kimashita ne", "en": "Your pronunciation is improving.", "context": "praise"}, {"id": 51, "mode": "strict_tutor", "jp": "答える前に助詞を数えて。", "romaji": "kotaeru mae ni joshi o kazoete", "en": "Count the particles before you answer.", "context": "drill"}, {"id": 52, "mode": "casual_friend", "jp": "アニメみたいな言い方だったね。", "romaji": "anime mitai na iikata datta ne", "en": "That sounded like something from an anime.", "context": "praise"}, {"id": 53, "mode": "immersion_mode", "jp": "今日のことを日本語で三文で説明して。", "romaji": "kyou no koto o nihongo de sanbun de setsumei shite", "en": "Describe your day in three Japanese sentences.", "context": "challenge"}, {"id": 122, "mode": "teacher", "jp": "小さく分けて考えましょう。", "romaji": "chiisaku wake te kangae mashou .", "en": "Break it into smaller pieces.", "context": "strategy"}, {"id": 123, "mode": "teacher", "jp": "話題の後の助詞に耳を傾けて。", "romaji": "wadai no nochino joshi ni mimi wo katamuke te .", "en": "Listen for the particle after the topic.", "context": "grammar_hint"}, {"id": 124, "mode": "teacher", "jp": "文の構造が良くなっています。", "romaji": "bun no kouzou ga yoku natteimasu .", "en": "Your sentence structure is improving.", "context": "praise"}, {"id": 125, "mode": "teacher", "jp": "一度声に出して読んでみて。", "romaji": "ichido koe ni dashi te yonde mite .", "en": "Try reading it aloud once.", "context": "practice"}, {"id": 126, "mode": "teacher", "jp": "どの部分が分かりにくいですか。", "romaji": "dono bubun ga waka rinikuidesuka .", "en": "What part feels unclear?", "context": "question"}, {"id": 127, "mode": "strict_tutor", "jp": "ここは主語。話題じゃない。", "romaji": "kokoha shugo . wadai janai .", "en": "Subject marker — not topic marker here.", "context": "correction"}, {"id": 128, "mode": "strict_tutor", "jp": "動詞の語尾は丁寧さに合わせて。", "romaji": "doushi no gobi ha teinei sani awa sete .", "en": "Verb ending must match politeness level.", "context": "correction"}, {"id": 129, "mode": "strict_tutor", "jp": "助詞が抜けています。", "romaji": "joshi ga nuke teimasu .", "en": "You skipped a particle.", "context": "correction"}, {"id": 130, "mode": "strict_tutor", "jp": "正しい形を五回繰り返して。", "romaji": "tadashii katachi wo gokai kurikaeshi te .", "en": "Repeat the correct form five times.", "context": "drill"}, {"id": 131, "mode": "strict_tutor", "jp": "一文でカジュアルと丁寧を混ぜない。", "romaji": "ichibun de kajuaru to teinei wo maze nai .", "en": "Do not mix casual and polite in one sentence.", "context": "rule"}, {"id": 132, "mode": "casual_friend", "jp": "自然に聞こえた！", "romaji": "shizen ni kiko eta !", "en": "That sounded natural!", "context": "praise"}, {"id": 133, "mode": "casual_friend", "jp": "あとでラーメン食べない？", "romaji": "atode raamen tabe nai ？", "en": "Wanna grab ramen later?", "context": "social"}, {"id": 134, "mode": "casual_friend", "jp": "俺ならこう言うかな…", "romaji": "ore narakou iu kana …", "en": "I would say it like this…", "context": "suggestion"}, {"id": 135, "mode": "casual_friend", "jp": "気にしないで。間違いは普通だよ。", "romaji": "kini shinaide . machigai ha futsuu dayo .", "en": "No stress — mistakes are normal.", "context": "encouragement"}, {"id": 136, "mode": "casual_friend", "jp": "アニメ語彙が出てきたね。", "romaji": "anime goi ga dete kitane .", "en": "Your anime vocab is showing.", "context": "joke"}, {"id": 137, "mode": "immersion_mode", "jp": "日本語だけで返事して。", "romaji": "nihongo dakede henji shite .", "en": "Reply in Japanese only.", "context": "immersion"}, {"id": 138, "mode": "immersion_mode", "jp": "周りを見て、日本語で説明して。", "romaji": "mawari wo mite , nihongo de setsumeishi te .", "en": "Describe what you see around you.", "context": "challenge"}, {"id": 139, "mode": "immersion_mode", "jp": "翻訳する前に、日本語で考えて。", "romaji": "honyaku suru mae ni , nihongo de kangae te .", "en": "Think before you translate.", "context": "immersion"}, {"id": 140, "mode": "immersion_mode", "jp": "今回はローマ字なし。", "romaji": "konkai ha rooma ji nashi .", "en": "No romaji this turn.", "context": "immersion"}, {"id": 141, "mode": "immersion_mode", "jp": "今日のことを三文で教えて。", "romaji": "kyou nokotowo sanmon de oshie te .", "en": "Tell me about your day in three sentences.", "context": "challenge"}, {"id": 254, "mode": "strict", "jp": null, "romaji": "", "en": "You already know this grammar point. Try again.", "context": "extended_pack"}, {"id": 255, "mode": "casual", "jp": null, "romaji": "", "en": "Nice, that sounded way more natural.", "context": "extended_pack"}, {"id": 256, "mode": "immersion", "jp": "日本語だけで話しましょう。", "romaji": "nihongo dakede hanashi mashou .", "en": "(immersion line)", "context": "extended_pack"}]}